LICENSE.txt
MANIFEST.in
README.md
deployment.txt
setup.py
version.txt
programy/__init__.py
programy/activate.py
programy/binaries.py
programy/bot.py
programy/brain.py
programy/brainfactory.py
programy/braintree.py
programy/context.py
programy.egg-info/PKG-INFO
programy.egg-info/SOURCES.txt
programy.egg-info/dependency_links.txt
programy.egg-info/requires.txt
programy.egg-info/top_level.txt
programy/admin/__init__.py
programy/admin/tool.py
programy/admin/linux/__init__.py
programy/admin/linux/installer.py
programy/clients/__init__.py
programy/clients/args.py
programy/clients/botfactory.py
programy/clients/client.py
programy/clients/config.py
programy/clients/response.py
programy/clients/embed/__init__.py
programy/clients/embed/basic.py
programy/clients/embed/configfile.py
programy/clients/embed/datafile.py
programy/clients/embed/basicbot/basicbot.yaml
programy/clients/embed/basicbot/logging.yaml
programy/clients/embed/basicbot/categories/_template.aiml
programy/clients/embed/basicbot/categories/duplicates.aiml
programy/clients/embed/basicbot/categories/errors.aiml
programy/clients/embed/basicbot/categories/tests.aiml
programy/clients/embed/basicbot/categories/admin/client.aiml
programy/clients/embed/basicbot/categories/admin/hotreload.aiml
programy/clients/embed/basicbot/categories/admin/javascript.aiml
programy/clients/embed/basicbot/categories/admin/properties.aiml
programy/clients/embed/basicbot/categories/admin/rdf.aiml
programy/clients/embed/basicbot/categories/admin/scheduler.aiml
programy/clients/embed/basicbot/categories/admin/services.aiml
programy/clients/embed/basicbot/categories/admin/transcript.aiml
programy/clients/embed/basicbot/categories/core/defaults/comparisons.aiml
programy/clients/embed/basicbot/categories/core/defaults/defaults.aiml
programy/clients/embed/basicbot/categories/core/defaults/exit.aiml
programy/clients/embed/basicbot/categories/core/defaults/initial.aiml
programy/clients/embed/basicbot/categories/core/defaults/interjection.aiml
programy/clients/embed/basicbot/categories/core/defaults/udc.aiml
programy/clients/embed/basicbot/categories/core/defaults/unknown.aiml
