Metadata-Version: 2.1
Name: programy
Version: 5.0.1
Summary: AIML Framework and Platform
Home-page: https://github.com/keiffster/program-y.git
Author: Keith Sterling
Author-email: keiffster@gmail.com
License: UNKNOWN
Download-URL: https://github.com/keiffster/program-y/5.0.1.tar.gz
Keywords: aiml,chatbot,virtual assistant,ai
Platform: UNKNOWN
Classifier: Development Status :: 5 - Production/Stable
Classifier: Intended Audience :: Developers
Classifier: License :: OSI Approved :: MIT License
Classifier: Programming Language :: Python :: 3
Classifier: Programming Language :: Python :: 3.2
Classifier: Programming Language :: Python :: 3.3
Classifier: Programming Language :: Python :: 3.4
Classifier: Programming Language :: Python :: 3.5
Classifier: Programming Language :: Python :: 3.6
Classifier: Programming Language :: Python :: 3.7
